{
  "MaintenanceStrategy": "",
  "Description": "Time Based Desc",
  "ScheduleIndicator": "1",
  "StrategyUnit": "MON",
  "CallHorizon": "100",
  "FactoryCalendar": "GB",
  "AuthorizationGroup": "SMPM",
  "Package1": "10",
  "Package2": "15",
  "Package3": "20",
  "CycleLength1": "3",
  "CycleLength2": "6",
  "CycleLength3": "12",
  "Unit1": "Mon",
  "Unit2": "Mon",
  "Unit3": "Mon",
  "MaintenanceCycleText1": "3 Monthly",
  "MaintenanceCycleText2": "6 Monthly",
  "MaintenanceCycleText3": "1 Yearly",
  "CycleShortTextKey1": "3M",
  "CycleShortTextKey2": "6M",
  "CycleShortTextKey3": "1y",
  "Hierarchy1": "1",
  "Hierarchy2": "1",
  "Hierarchy3": "1",
  "HierarchyShortTextKey1": "H1",
  "HierarchyShortTextKey2": "H1",
  "HierarchyShortTextKey3": "H1"
}
